cymorton/__codec.cpp
cymorton/__codec.hpp
cymorton/__init__.py
cymorton/__main__.py
cymorton/cli.py
cymorton/codec.cpython-39-darwin.so
cymorton/codec.pxd
cymorton/codec.pyx
cymorton-0.0.2.dist-info/LICENSE
cymorton-0.0.2.dist-info/METADATA
cymorton-0.0.2.dist-info/WHEEL
cymorton-0.0.2.dist-info/entry_points.txt
cymorton-0.0.2.dist-info/top_level.txt
cymorton-0.0.2.dist-info/RECORD
